kaspa_script_address-0.0.1.dist-info/METADATA
kaspa_script_address-0.0.1.dist-info/WHEEL
kaspa_script_address-0.0.1.dist-info/licenses/LICENSE
kaspa_script_address/__init__.py
kaspa_script_address/kaspa_script_address.abi3.so
kaspa_script_address-0.0.1.dist-info/RECORD
