Metadata-Version: 2.4
Name: kaspa_script_address
Version: 0.0.1
License-File: LICENSE
Author: suprtypo@pm.me
Author-email: suprtypo@pm.me
